LICENSE
README.md
pyproject.toml
pyglet_particles/__init__.py
pyglet_particles/particles.py
pyglet_particles/physics.py
pyglet_particles.egg-info/PKG-INFO
pyglet_particles.egg-info/SOURCES.txt
pyglet_particles.egg-info/dependency_links.txt
pyglet_particles.egg-info/requires.txt
pyglet_particles.egg-info/top_level.txt
venv/Lib/site-packages/_virtualenv.py
venv/Lib/site-packages/_distutils_hack/__init__.py
venv/Lib/site-packages/_distutils_hack/override.py
venv/Lib/site-packages/backports/__init__.py
venv/Lib/site-packages/backports/tarfile/__init__.py
venv/Lib/site-packages/backports/tarfile/__main__.py
venv/Lib/site-packages/backports/tarfile/compat/__init__.py
venv/Lib/site-packages/backports/tarfile/compat/py38.py
venv/Lib/site-packages/build/__init__.py
venv/Lib/site-packages/build/__main__.py
venv/Lib/site-packages/build/_builder.py
venv/Lib/site-packages/build/_ctx.py
venv/Lib/site-packages/build/_exceptions.py
venv/Lib/site-packages/build/_types.py
venv/Lib/site-packages/build/_util.py
venv/Lib/site-packages/build/env.py
venv/Lib/site-packages/build/py.typed
venv/Lib/site-packages/build/util.py
venv/Lib/site-packages/build/_compat/__init__.py
venv/Lib/site-packages/build/_compat/importlib.py
venv/Lib/site-packages/build/_compat/tarfile.py
venv/Lib/site-packages/build/_compat/tomllib.py
venv/Lib/site-packages/certifi/__init__.py
venv/Lib/site-packages/certifi/__main__.py
venv/Lib/site-packages/certifi/core.py
venv/Lib/site-packages/certifi/py.typed
venv/Lib/site-packages/charset_normalizer/__init__.py
venv/Lib/site-packages/charset_normalizer/__main__.py
venv/Lib/site-packages/charset_normalizer/api.py
venv/Lib/site-packages/charset_normalizer/cd.py
venv/Lib/site-packages/charset_normalizer/constant.py
venv/Lib/site-packages/charset_normalizer/legacy.py
venv/Lib/site-packages/charset_normalizer/md.py
venv/Lib/site-packages/charset_normalizer/models.py
venv/Lib/site-packages/charset_normalizer/py.typed
venv/Lib/site-packages/charset_normalizer/utils.py
venv/Lib/site-packages/charset_normalizer/version.py
venv/Lib/site-packages/charset_normalizer/cli/__init__.py
venv/Lib/site-packages/charset_normalizer/cli/__main__.py
