Metadata-Version: 2.1
Name: pyglet_particles
Version: 1.0.1
Author: Sombra Studio
Project-URL: Homepage, https://github.com/sombra-studio/pyglet-particle-system
Project-URL: Issues, https://github.com/sombra-studio/pyglet-particle-system/issues
Classifier: Programming Language :: Python :: 3
Classifier: License :: OSI Approved :: MIT License
Classifier: Operating System :: OS Independent
Requires-Python: >=3.7
License-File: LICENSE
Requires-Dist: numpy
Requires-Dist: pyglet
